pyfortified_dateutil/__init__.py
pyfortified_dateutil-0.1.1.dist-info/METADATA
pyfortified_dateutil-0.1.1.dist-info/RECORD
pyfortified_dateutil-0.1.1.dist-info/WHEEL
pyfortified_dateutil-0.1.1.dist-info/top_level.txt
