Metadata-Version: 2.1
Name: pyfortified-dateutil
Version: 0.1.1
Summary: Extension to Python `datetime` functionality.
Home-page: https://github.com/jeff00seattle/pyfortified-dateutil
Author: UNKNOWN
Author-email: UNKNOWN
License: MIT License
Download-URL: https://github.com/jeff00seattle/pyfortified-dateutil/archive/v0.1.1.tar.gz
Keywords: pyfortified dateutil
Platform: UNKNOWN
Classifier: Development Status :: 3 - Alpha
Classifier: Intended Audience :: Developers
Classifier: Natural Language :: English
Classifier: License :: OSI Approved :: MIT License
Classifier: Operating System :: OS Independent
Classifier: Natural Language :: English
Classifier: Programming Language :: Python
Classifier: Programming Language :: Python :: 3
Classifier: Programming Language :: Python :: 3.4
Classifier: Programming Language :: Python :: 3.5
Classifier: Programming Language :: Python :: 3.6
Classifier: Topic :: Software Development :: Libraries :: Python Modules
Requires-Dist: pprintpp
Requires-Dist: python-dateutil (>=2.7.3)
Requires-Dist: pytz (>=2018.4)
Requires-Dist: pytz-convert
Requires-Dist: safe-cast
Requires-Dist: tzlocal (>=1.5.1)
Requires-Dist: wheel (>=0.30.0)
